dbmail/__init__.py
dbmail/admin.py
dbmail/apps.py
dbmail/defaults.py
dbmail/exceptions.py
dbmail/fields.py
dbmail/models.py
dbmail/signals.py
dbmail/tasks.py
dbmail/test_cases.py
dbmail/translation.py
dbmail/urls.py
dbmail/utils.py
dbmail/views.py
dbmail/backends/__init__.py
dbmail/backends/bot.py
dbmail/backends/mail.py
dbmail/backends/push.py
dbmail/backends/sms.py
dbmail/backends/tts.py
dbmail/fixtures/mailgun_base_templates.json
dbmail/locale/ru/LC_MESSAGES/django.mo
dbmail/locale/ru/LC_MESSAGES/django.po
dbmail/management/__init__.py
dbmail/management/commands/__init__.py
dbmail/management/commands/clean_dbmail_cache.py
dbmail/management/commands/clean_dbmail_logs.py
dbmail/management/commands/dbmail_test_send.py
dbmail/management/commands/load_dbmail_base_templates.py
dbmail/management/commands/send_dbmail_deferred_signal.py
dbmail/management/commands/update_dbmail_cache.py
dbmail/migrations/0001_initial.py
dbmail/migrations/0002_auto_20150321_1539.py
dbmail/migrations/0003_maillog_backend.py
dbmail/migrations/0004_auto_20150321_2214.py
dbmail/migrations/0005_auto_20150506_2201.py
dbmail/migrations/0006_auto_20150708_0714.py
dbmail/migrations/0007_auto_20150708_2016.py
dbmail/migrations/0008_auto_20151007_1918.py
dbmail/migrations/0009_auto_20160311_0918.py
dbmail/migrations/0010_auto_20160728_1645.py
dbmail/migrations/0011_auto_20160803_1024.py
dbmail/migrations/0012_auto_20160915_1340.py
dbmail/migrations/0013_auto_20160923_2201.py
dbmail/migrations/0014_auto_20170801_1206.py
dbmail/migrations/__init__.py
dbmail/providers/__init__.py
dbmail/providers/apple/__init__.py
dbmail/providers/apple/apns.py
dbmail/providers/apple/apns2.py
dbmail/providers/apple/errors.py
dbmail/providers/boxcar/__init__.py
dbmail/providers/boxcar/push.py
dbmail/providers/centrifugo/__init__.py
dbmail/providers/centrifugo/push.py
dbmail/providers/google/__init__.py
dbmail/providers/google/android.py
django_db_mailer-2.3.19.dist-info/DESCRIPTION.rst
django_db_mailer-2.3.19.dist-info/METADATA
django_db_mailer-2.3.19.dist-info/RECORD
django_db_mailer-2.3.19.dist-info/WHEEL
django_db_mailer-2.3.19.dist-info/metadata.json
django_db_mailer-2.3.19.dist-info/top_level.txt
