Metadata-Version: 2.0
Name: django-db-mailer
Version: 2.3.19
Summary: Django module to easily send emails using django templates stored in a database.
Home-page: http://github.com/LPgenerator/django-db-mailer/
Author: GoTLiuM InSPiRiT
Author-email: gotlium@gmail.com
License: UNKNOWN
Keywords: django db mail email html text tts sms push templates mailer
Platform: UNKNOWN
Classifier: Development Status :: 5 - Production/Stable
Classifier: Environment :: Web Environment
Classifier: Framework :: Django
Classifier: Intended Audience :: Developers
Classifier: License :: OSI Approved :: GNU General Public License (GPL)
Classifier: Operating System :: OS Independent
Classifier: Programming Language :: Python
Classifier: Programming Language :: Python :: 2
Classifier: Programming Language :: Python :: 2.7
Classifier: Programming Language :: Python :: 3
Classifier: Programming Language :: Python :: 3.4
Classifier: Programming Language :: Python :: 3.5
Classifier: Topic :: Internet :: WWW/HTTP
Classifier: Topic :: Software Development :: Libraries :: Python Modules
Requires-Dist: setuptools
